msp2db/__init__.py
msp2db/__main__.py
msp2db/db.py
msp2db/parse.py
msp2db/re.py
msp2db/utils.py
tests/__init__.py
tests/test_msp2db.py
msp2db-0.0.9.dist-info/LICENSE
msp2db-0.0.9.dist-info/METADATA
msp2db-0.0.9.dist-info/WHEEL
msp2db-0.0.9.dist-info/entry_points.txt
msp2db-0.0.9.dist-info/top_level.txt
msp2db-0.0.9.dist-info/RECORD
