Metadata-Version: 2.1
Name: msp2db
Version: 0.0.9
Summary: Python package for converting msp to database
Home-page: https://github.com/computational-metabolomics/msp2db
Author: Thomas N. Lawson
Author-email: t.n.lawson@bham.ac.uk
License: GPLv3
Keywords: Metabolomics,Lipidomics,Mass spectrometry,Data Processing,Fragmentation
Platform: Windows, UNIX
Classifier: Programming Language :: Python :: 2
Classifier: Programming Language :: Python :: 2.7
Classifier: Programming Language :: Python :: 3
Classifier: Programming Language :: Python :: 3.6
Classifier: Topic :: Scientific/Engineering :: Bio-Informatics
Classifier: Topic :: Scientific/Engineering :: Chemistry
Classifier: Topic :: Utilities
Classifier: License :: OSI Approved :: GNU General Public License v3 (GPLv3)
Classifier: Operating System :: OS Independent
Requires-Dist: pubchempy
Requires-Dist: six
